trad/__init__.py
trad/plasma.py
trad/solution.py
trad/specradiance.py
trad/sync/Dexter2016.py
trad/sync/LeungX2011.py
trad/sync/__init__.py
trad/units.py
trad-0.1.4.dist-info/LICENSE
trad-0.1.4.dist-info/METADATA
trad-0.1.4.dist-info/WHEEL
trad-0.1.4.dist-info/RECORD
